tango_checkup/__init__.py
tango_checkup/_version.py
tango_checkup/checks.py
tango_checkup/decorators.py
tango_checkup/fixtures.py
tango_checkup/getters.py
tango_checkup/hooks.py
tango_checkup/plugin.py
tango_checkup/report.py
tango_checkup/templates/base.html
tango_checkup-0.1.2.dist-info/LICENSE
tango_checkup-0.1.2.dist-info/METADATA
tango_checkup-0.1.2.dist-info/WHEEL
tango_checkup-0.1.2.dist-info/entry_points.txt
tango_checkup-0.1.2.dist-info/top_level.txt
tango_checkup-0.1.2.dist-info/RECORD
