Metadata-Version: 2.1
Name: tango-checkup
Version: 0.1.2
Summary: Pytest fixtures and helpers for checking the health of a Tango control system.
Author-email: MAX IV KITS Software <kits-sw@maxiv.lu.se>
License: GNU GENERAL PUBLIC LICENSE
Requires-Python: >=3.10
License-File: LICENSE
Requires-Dist: pytest
Requires-Dist: pytest-metadata
Requires-Dist: pytest-reportlog
Requires-Dist: pytango
Requires-Dist: jinja2
